graphene_djmoney/__init__.py
graphene_djmoney/schema/__init__.py
graphene_djmoney/schema/types.py
graphene_djmoney-0.2.3.dist-info/LICENSE.md
graphene_djmoney-0.2.3.dist-info/METADATA
graphene_djmoney-0.2.3.dist-info/WHEEL
graphene_djmoney-0.2.3.dist-info/RECORD
