Metadata-Version: 2.1
Name: graphene-djmoney
Version: 0.2.3
Summary: GraphQL Money types for Django using graphene and django-money (djmoney).
Home-page: https://github.com/UpliftAgency/graphene-djmoney
License: MIT
Keywords: graphene,djmoney,moneyed,graphql,money,currency
Author: Paul Craciunoiu
Author-email: paul@craciunoiu.net
Requires-Python: >=3.7,<4.0
Classifier: License :: OSI Approved :: MIT License
Classifier: Programming Language :: Python :: 3
Classifier: Programming Language :: Python :: 3.7
Classifier: Programming Language :: Python :: 3.8
Classifier: Programming Language :: Python :: 3.9
Classifier: Programming Language :: Python :: 3.10
Classifier: Programming Language :: Python :: 3.11
Requires-Dist: Django (>2)
Requires-Dist: django-money (>=3.0.0,<4.0.0)
Requires-Dist: graphene (>=2.1.7,<3)
Requires-Dist: graphene-django (>=2)
Requires-Dist: graphql-core (>=2.1.0)
Requires-Dist: psycopg2-binary (>=2.8.5,<3.0.0)
Project-URL: Repository, https://github.com/UpliftAgency/graphene-djmoney
